arithm4child/__init__.py
arithm4child/arithm4child.py
arithm4child-1.6.dist-info/LICENSE
arithm4child-1.6.dist-info/METADATA
arithm4child-1.6.dist-info/WHEEL
arithm4child-1.6.dist-info/entry_points.txt
arithm4child-1.6.dist-info/top_level.txt
arithm4child-1.6.dist-info/RECORD
