Metadata-Version: 2.1
Name: arithm4child
Version: 1.6
Summary: arithmetic quiz for children
Home-page: https://github.com/baiwensimi/arithm4child
Author: Bai Wensimi
Author-email: baiwensimi@gmail.com
License: UNKNOWN
Platform: UNKNOWN
Classifier: Programming Language :: Python :: 3
Classifier: License :: OSI Approved :: Apache Software License
Classifier: Operating System :: OS Independent
Requires-Python: >=3.6
